{
"meta":{"test_sets":[],"test_metrics":[],"learn_metrics":[{"best_value":"Min","name":"MultiClass"}],"launch_mode":"Train","parameters":"","iteration_count":100,"learn_sets":["learn"],"name":"experiment"},
"iterations":[
{"learn":[2.797388968],"iteration":0,"passed_time":0.3153774055,"remaining_time":31.22236315},
{"learn":[2.431893203],"iteration":1,"passed_time":0.4241798827,"remaining_time":20.78481425},
{"learn":[2.337321486],"iteration":2,"passed_time":0.4751562641,"remaining_time":15.36338587},
{"learn":[2.295157973],"iteration":3,"passed_time":0.5216207255,"remaining_time":12.51889741},
{"learn":[2.271947242],"iteration":4,"passed_time":0.5715655468,"remaining_time":10.85974539},
{"learn":[2.257954903],"iteration":5,"passed_time":0.6229237083,"remaining_time":9.759138097},
{"learn":[2.243030405],"iteration":6,"passed_time":0.6757742624,"remaining_time":8.978143771},
{"learn":[2.223650005],"iteration":7,"passed_time":0.7456183648,"remaining_time":8.574611195},
{"learn":[2.213155177],"iteration":8,"passed_time":0.8662445331,"remaining_time":8.758694723},
{"learn":[2.206750579],"iteration":9,"passed_time":0.9831382569,"remaining_time":8.848244312},
{"learn":[2.193741271],"iteration":10,"passed_time":1.097084426,"remaining_time":8.876410354},
{"learn":[2.18650427],"iteration":11,"passed_time":1.216031844,"remaining_time":8.917566855},
{"learn":[2.17906327],"iteration":12,"passed_time":1.328859976,"remaining_time":8.89313984},
{"learn":[2.167626448],"iteration":13,"passed_time":1.441101718,"remaining_time":8.852481985},
{"learn":[2.162265732],"iteration":14,"passed_time":1.514752584,"remaining_time":8.583597974},
{"learn":[2.154653701],"iteration":15,"passed_time":1.589536156,"remaining_time":8.345064821},
{"learn":[2.14648115],"iteration":16,"passed_time":1.664005868,"remaining_time":8.124263942},
{"learn":[2.139124126],"iteration":17,"passed_time":1.73962847,"remaining_time":7.92497414},
{"learn":[2.133283713],"iteration":18,"passed_time":1.823107349,"remaining_time":7.772194486},
{"learn":[2.124379574],"iteration":19,"passed_time":1.905405809,"remaining_time":7.621623234},
{"learn":[2.114718694],"iteration":20,"passed_time":1.985357276,"remaining_time":7.468724989},
{"learn":[2.10618437],"iteration":21,"passed_time":2.06704975,"remaining_time":7.328630933},
{"learn":[2.096735838],"iteration":22,"passed_time":2.150986941,"remaining_time":7.201130194},
{"learn":[2.091094005],"iteration":23,"passed_time":2.235097025,"remaining_time":7.077807247},
{"learn":[2.081758958],"iteration":24,"passed_time":2.322420941,"remaining_time":6.967262822},
{"learn":[2.069625904],"iteration":25,"passed_time":2.409621141,"remaining_time":6.858152478},
{"learn":[2.062720598],"iteration":26,"passed_time":2.486860679,"remaining_time":6.723734429},
{"learn":[2.054663069],"iteration":27,"passed_time":2.568603142,"remaining_time":6.604979508},
{"learn":[2.046358529],"iteration":28,"passed_time":2.657773708,"remaining_time":6.506963217},
{"learn":[2.042487569],"iteration":29,"passed_time":2.739322269,"remaining_time":6.391751961},
{"learn":[2.031860859],"iteration":30,"passed_time":2.814029913,"remaining_time":6.263485936},
{"learn":[2.023201943],"iteration":31,"passed_time":2.894148248,"remaining_time":6.150065026},
{"learn":[2.012001444],"iteration":32,"passed_time":2.971339363,"remaining_time":6.032719312},
{"learn":[2.009955654],"iteration":33,"passed_time":3.046176125,"remaining_time":5.913165419},
{"learn":[2.004436867],"iteration":34,"passed_time":3.125044958,"remaining_time":5.803654923},
{"learn":[1.996471063],"iteration":35,"passed_time":3.220079664,"remaining_time":5.724586069},
{"learn":[1.99057165],"iteration":36,"passed_time":3.328864369,"remaining_time":5.668066359},
{"learn":[1.984764492],"iteration":37,"passed_time":3.432602721,"remaining_time":5.600562335},
{"learn":[1.980255078],"iteration":38,"passed_time":3.534467527,"remaining_time":5.528269722},
{"learn":[1.976574219],"iteration":39,"passed_time":3.640879641,"remaining_time":5.461319461},
{"learn":[1.969385762],"iteration":40,"passed_time":3.752842666,"remaining_time":5.400432129},
{"learn":[1.966427663],"iteration":41,"passed_time":3.857354883,"remaining_time":5.32682341},
{"learn":[1.96275504],"iteration":42,"passed_time":3.967048577,"remaining_time":5.258645788},
{"learn":[1.961136108],"iteration":43,"passed_time":4.089805905,"remaining_time":5.205207516},
{"learn":[1.954345307],"iteration":44,"passed_time":4.172859817,"remaining_time":5.100161999},
{"learn":[1.95048704],"iteration":45,"passed_time":4.232548668,"remaining_time":4.968644088},
{"learn":[1.946810795],"iteration":46,"passed_time":4.28548679,"remaining_time":4.83257021},
{"learn":[1.94439348],"iteration":47,"passed_time":4.346209906,"remaining_time":4.708394065},
{"learn":[1.940350647],"iteration":48,"passed_time":4.409581653,"remaining_time":4.589564578},
{"learn":[1.931132651],"iteration":49,"passed_time":4.466645404,"remaining_time":4.466645404},
{"learn":[1.924655241],"iteration":50,"passed_time":4.539076069,"remaining_time":4.361073086},
{"learn":[1.919433983],"iteration":51,"passed_time":4.610767963,"remaining_time":4.256093504},
{"learn":[1.914274466],"iteration":52,"passed_time":4.702442341,"remaining_time":4.170090378},
{"learn":[1.906980147],"iteration":53,"passed_time":4.820474308,"remaining_time":4.106329966},
{"learn":[1.902535929],"iteration":54,"passed_time":4.944866741,"remaining_time":4.045800061},
{"learn":[1.897917136],"iteration":55,"passed_time":5.001279112,"remaining_time":3.929576445},
{"learn":[1.894726358],"iteration":56,"passed_time":5.062911928,"remaining_time":3.8193897},
{"learn":[1.890651147],"iteration":57,"passed_time":5.115935352,"remaining_time":3.704642841},
{"learn":[1.888559947],"iteration":58,"passed_time":5.190101502,"remaining_time":3.606680705},
{"learn":[1.884636319],"iteration":59,"passed_time":5.290515369,"remaining_time":3.527010246},
{"learn":[1.878654761],"iteration":60,"passed_time":5.399080835,"remaining_time":3.451871353},
{"learn":[1.875648602],"iteration":61,"passed_time":5.506676203,"remaining_time":3.375059608},
{"learn":[1.87119324],"iteration":62,"passed_time":5.620856385,"remaining_time":3.301137877},
{"learn":[1.867901247],"iteration":63,"passed_time":5.733833616,"remaining_time":3.225281409},
{"learn":[1.864205743],"iteration":64,"passed_time":5.852413408,"remaining_time":3.151299527},
{"learn":[1.861682197],"iteration":65,"passed_time":5.961876252,"remaining_time":3.071269584},
{"learn":[1.857217341],"iteration":66,"passed_time":6.078225436,"remaining_time":2.993752826},
{"learn":[1.854924403],"iteration":67,"passed_time":6.189301224,"remaining_time":2.912612341},
{"learn":[1.850005652],"iteration":68,"passed_time":6.303818995,"remaining_time":2.832150563},
{"learn":[1.846187283],"iteration":69,"passed_time":6.406922891,"remaining_time":2.745824096},
{"learn":[1.843085588],"iteration":70,"passed_time":6.516341939,"remaining_time":2.661604454},
{"learn":[1.839170126],"iteration":71,"passed_time":6.616651328,"remaining_time":2.573142183},
{"learn":[1.837207819],"iteration":72,"passed_time":6.718455575,"remaining_time":2.484908226},
{"learn":[1.832386976],"iteration":73,"passed_time":6.816090285,"remaining_time":2.394842533},
{"learn":[1.83119133],"iteration":74,"passed_time":6.910065675,"remaining_time":2.303355225},
{"learn":[1.82798809],"iteration":75,"passed_time":7.020502686,"remaining_time":2.217000848},
{"learn":[1.822392518],"iteration":76,"passed_time":7.129096302,"remaining_time":2.129470324},
{"learn":[1.819357329],"iteration":77,"passed_time":7.228005363,"remaining_time":2.038668179},
{"learn":[1.815590207],"iteration":78,"passed_time":7.33083928,"remaining_time":1.948704112},
{"learn":[1.812203669],"iteration":79,"passed_time":7.42791987,"remaining_time":1.856979967},
{"learn":[1.809165494],"iteration":80,"passed_time":7.533836471,"remaining_time":1.767196209},
{"learn":[1.804831146],"iteration":81,"passed_time":7.638443306,"remaining_time":1.676731457},
{"learn":[1.802419323],"iteration":82,"passed_time":7.740670795,"remaining_time":1.585438597},
{"learn":[1.801299012],"iteration":83,"passed_time":7.841065716,"remaining_time":1.493536327},
{"learn":[1.799301252],"iteration":84,"passed_time":7.939334772,"remaining_time":1.401059077},
{"learn":[1.797187534],"iteration":85,"passed_time":8.067826872,"remaining_time":1.313367165},
{"learn":[1.794256543],"iteration":86,"passed_time":8.180512432,"remaining_time":1.222375421},
{"learn":[1.791778287],"iteration":87,"passed_time":8.289313267,"remaining_time":1.1303609},
{"learn":[1.787238919],"iteration":88,"passed_time":8.401740489,"remaining_time":1.038417364},
{"learn":[1.785613686],"iteration":89,"passed_time":8.515371072,"remaining_time":0.9461523413},
{"learn":[1.781850022],"iteration":90,"passed_time":8.630043596,"remaining_time":0.8535207952},
{"learn":[1.778941565],"iteration":91,"passed_time":8.743556415,"remaining_time":0.7603092535},
{"learn":[1.777413476],"iteration":92,"passed_time":8.854236588,"remaining_time":0.6664479152},
{"learn":[1.775528999],"iteration":93,"passed_time":8.961159378,"remaining_time":0.5719888964},
{"learn":[1.77317341],"iteration":94,"passed_time":9.077611382,"remaining_time":0.4777690201},
{"learn":[1.771255944],"iteration":95,"passed_time":9.191520755,"remaining_time":0.3829800315},
{"learn":[1.765936696],"iteration":96,"passed_time":9.306457937,"remaining_time":0.287828596},
{"learn":[1.762763742],"iteration":97,"passed_time":9.417291812,"remaining_time":0.1921896288},
{"learn":[1.759898093],"iteration":98,"passed_time":9.531741339,"remaining_time":0.09628021555},
{"learn":[1.756312935],"iteration":99,"passed_time":9.641136258,"remaining_time":0}
]}